utic_cache/__init__.py
utic_cache/compat.py
utic_cache/containers/__init__.py
utic_cache/containers/lru.py
utic_cache/containers/ttl.py
utic_cache/controls.py
utic_cache/key.py
utic_cache-2.2.2.dist-info/LICENSE
utic_cache-2.2.2.dist-info/METADATA
utic_cache-2.2.2.dist-info/WHEEL
utic_cache-2.2.2.dist-info/RECORD
