Metadata-Version: 2.3
Name: utic-cache
Version: 2.2.2
Summary: An asyncio Cache
License: MIT
Keywords: asyncio,lru,cache,async,cache,lru-cache,ttl
Author: lightmanLP
Author-email: liteman1000@gmail.com
Requires-Python: >=3.10
Classifier: License :: OSI Approved :: MIT License
Classifier: Operating System :: OS Independent
Classifier: Programming Language :: Python :: 3
Classifier: Programming Language :: Python :: 3.10
Classifier: Programming Language :: Python :: 3.11
Classifier: Programming Language :: Python :: 3.12
Classifier: Programming Language :: Python :: 3.13
Project-URL: Homepage, https://github.com/UT1C/async-cache
Project-URL: Repository, https://github.com/UT1C/async-cache
